dbt/README.md
dbt/__init__.py
dbt/compilation.py
dbt/constants.py
dbt/deprecations.py
dbt/exceptions.py
dbt/flags.py
dbt/hooks.py
dbt/internal_deprecations.py
dbt/links.py
dbt/mp_context.py
dbt/node_types.py
dbt/profiler.py
dbt/py.typed
dbt/selected_resources.py
dbt/tracking.py
dbt/utils.py
dbt/version.py
dbt/artifacts/README.md
dbt/artifacts/__init__.py
dbt/artifacts/exceptions/__init__.py
dbt/artifacts/exceptions/schemas.py
dbt/artifacts/resources/__init__.py
dbt/artifacts/resources/base.py
dbt/artifacts/resources/types.py
dbt/artifacts/resources/v1/analysis.py
dbt/artifacts/resources/v1/components.py
dbt/artifacts/resources/v1/config.py
dbt/artifacts/resources/v1/documentation.py
dbt/artifacts/resources/v1/exposure.py
dbt/artifacts/resources/v1/generic_test.py
dbt/artifacts/resources/v1/group.py
dbt/artifacts/resources/v1/hook.py
dbt/artifacts/resources/v1/macro.py
dbt/artifacts/resources/v1/metric.py
dbt/artifacts/resources/v1/model.py
dbt/artifacts/resources/v1/owner.py
dbt/artifacts/resources/v1/saved_query.py
dbt/artifacts/resources/v1/seed.py
dbt/artifacts/resources/v1/semantic_layer_components.py
dbt/artifacts/resources/v1/semantic_model.py
dbt/artifacts/resources/v1/singular_test.py
dbt/artifacts/resources/v1/snapshot.py
dbt/artifacts/resources/v1/source_definition.py
dbt/artifacts/resources/v1/sql_operation.py
dbt/artifacts/resources/v1/unit_test_definition.py
dbt/artifacts/schemas/__init__.py
dbt/artifacts/schemas/base.py
dbt/artifacts/schemas/batch_results.py
dbt/artifacts/schemas/results.py
dbt/artifacts/schemas/catalog/__init__.py
dbt/artifacts/schemas/catalog/v1/__init__.py
dbt/artifacts/schemas/catalog/v1/catalog.py
dbt/artifacts/schemas/freshness/__init__.py
dbt/artifacts/schemas/freshness/v3/__init__.py
dbt/artifacts/schemas/freshness/v3/freshness.py
dbt/artifacts/schemas/manifest/__init__.py
dbt/artifacts/schemas/manifest/v12/__init__.py
dbt/artifacts/schemas/manifest/v12/manifest.py
dbt/artifacts/schemas/run/__init__.py
in_dbt_core-1.9.7.dist-info/METADATA
in_dbt_core-1.9.7.dist-info/WHEEL
in_dbt_core-1.9.7.dist-info/entry_points.txt
in_dbt_core-1.9.7.dist-info/top_level.txt
in_dbt_core-1.9.7.dist-info/RECORD
